nproan/__init__.py
nproan/analysis.py
nproan/display.py
nproan/file_io.py
nproan/fitting.py
nproan/logger.py
nproan/params.py
nproan/pyroot_funcs.py
nproan/roan_steps.py
nproan/utils.py
nproan-0.0.4.dist-info/METADATA
nproan-0.0.4.dist-info/WHEEL
nproan-0.0.4.dist-info/licenses/LICENSE
nproan-0.0.4.dist-info/RECORD
