Metadata-Version: 2.3
Name: nproan
Version: 0.0.4
Summary: Tools for analysis of data from the DANAE experiment on HEPHY
Project-URL: Homepage, https://github.com/shakamaran/nproan
Project-URL: Issues, https://github.com/shakamaran/nproan/issues
Author-email: Florian Heinrich <florianheinrich@gmx.at>
License-File: LICENSE
Classifier: License :: OSI Approved :: MIT License
Classifier: Operating System :: OS Independent
Classifier: Programming Language :: Python :: 3
Requires-Python: >=3.8
